aprsd_telegram_plugin/__init__.py
aprsd_telegram_plugin/telegram.py
aprsd_telegram_plugin-0.1.3.dist-info/LICENSE
aprsd_telegram_plugin-0.1.3.dist-info/METADATA
aprsd_telegram_plugin-0.1.3.dist-info/WHEEL
aprsd_telegram_plugin-0.1.3.dist-info/pbr.json
aprsd_telegram_plugin-0.1.3.dist-info/top_level.txt
aprsd_telegram_plugin-0.1.3.dist-info/RECORD
