Metadata-Version: 2.1
Name: aprsd-telegram-plugin
Version: 0.1.3
Summary: Ham Radio APRS APRSD plugin for Telegram IM service
Home-page: UNKNOWN
Author: Walter A. Boring IV
Author-email: waboring@hemna.com
License: MIT
Platform: UNKNOWN
Classifier: Topic :: Communications :: Ham Radio
Classifier: Operating System :: POSIX :: Linux
Classifier: Programming Language :: Python
Classifier: Programming Language :: Python :: 3.7
Classifier: Programming Language :: Python :: 3.8
Classifier: Programming Language :: Python :: 3.9
License-File: LICENSE
Requires-Dist: pbr
Requires-Dist: aprsd (>=2.4.0)
Requires-Dist: python-telegram-bot
